onnxocr/__init__.py
onnxocr/cls_postprocess.py
onnxocr/db_postprocess.py
onnxocr/imaug.py
onnxocr/logger.py
onnxocr/ocr_images_pdfs.py
onnxocr/onnx_paddleocr.py
onnxocr/operators.py
onnxocr/predict_base.py
onnxocr/predict_cls.py
onnxocr/predict_det.py
onnxocr/predict_rec.py
onnxocr/predict_system.py
onnxocr/rec_postprocess.py
onnxocr/utils.py
onnxocr/models/ppocrv4/ppocrv4_dict.txt
onnxocr/models/ppocrv4/det/det.onnx
onnxocr/models/ppocrv4/rec/rec.onnx
onnxocr_ppocrv4-0.0.5.dist-info/licenses/LICENSE
onnxocr_ppocrv4-0.0.5.dist-info/METADATA
onnxocr_ppocrv4-0.0.5.dist-info/WHEEL
onnxocr_ppocrv4-0.0.5.dist-info/top_level.txt
onnxocr_ppocrv4-0.0.5.dist-info/RECORD
