Metadata-Version: 2.4
Name: onnxocr-ppocrv4
Version: 0.0.5
Summary: ONNX-based OCR (PP-OCRv5) inference pipeline with DirectML support.
Author-email: Your Name <your.email@example.com>
License:                                  Apache License
Project-URL: Homepage, https://github.com/ok-oldking/OnnxOCR
Project-URL: Repository, https://github.com/ok-oldking/OnnxOCR
Project-URL: Issues, https://github.com/ok-oldking/OnnxOCR/issues
Keywords: ocr,onnx,directml,ppocr,text detection,text recognition
Classifier: Development Status :: 3 - Alpha
Classifier: Intended Audience :: Developers
Classifier: Intended Audience :: Science/Research
Classifier: License :: OSI Approved :: Apache Software License
Classifier: Operating System :: OS Independent
Classifier: Programming Language :: Python :: 3
Classifier: Programming Language :: Python :: 3.8
Classifier: Programming Language :: Python :: 3.9
Classifier: Programming Language :: Python :: 3.10
Classifier: Programming Language :: Python :: 3.11
Classifier: Topic :: Scientific/Engineering :: Image Recognition
Classifier: Topic :: Software Development :: Libraries :: Python Modules
Requires-Python: >=3.8
License-File: LICENSE
Requires-Dist: pyclipper
Requires-Dist: shapely
Requires-Dist: pillow
Dynamic: license-file
